jumprun.py
jumprun-1.12.dist-info/DESCRIPTION.rst
jumprun-1.12.dist-info/entry_points.txt
jumprun-1.12.dist-info/METADATA
jumprun-1.12.dist-info/metadata.json
jumprun-1.12.dist-info/RECORD
jumprun-1.12.dist-info/top_level.txt
jumprun-1.12.dist-info/WHEEL
