Metadata-Version: 2.0
Name: jumprun
Version: 1.12
Summary: Command-line utility to create shortcuts for running scripts
Home-page: http://github.com/itsnauman/jumprun
Author: Nauman Ahmad
Author-email: nauman-ahmad@outlook.com
License: MIT
Platform: UNKNOWN
Requires-Dist: termcolor
Requires-Dist: docopt
